tobiko/__init__.py
tobiko/config.py
tobiko/version.py
tobiko/cmd/__init__.py
tobiko/cmd/_http_ping.py
tobiko/cmd/_main.py
tobiko/cmd/_ping.py
tobiko/common/__init__.py
tobiko/common/_cached.py
tobiko/common/_case.py
tobiko/common/_config.py
tobiko/common/_detail.py
tobiko/common/_exception.py
tobiko/common/_fixture.py
tobiko/common/_ini.py
tobiko/common/_loader.py
tobiko/common/_lockutils.py
tobiko/common/_logging.py
tobiko/common/_operation.py
tobiko/common/_os.py
tobiko/common/_retry.py
tobiko/common/_select.py
tobiko/common/_shelves.py
tobiko/common/_skip.py
tobiko/common/_tabledata.py
tobiko/common/_time.py
tobiko/common/_utils.py
tobiko/common/_version.py
tobiko/common/_yaml.py
tobiko/http/__init__.py
tobiko/http/_connection.py
tobiko/http/_session.py
tobiko/openstack/__init__.py
tobiko/openstack/_client.py
tobiko/openstack/base/__init__.py
tobiko/openstack/base/_fixture.py
tobiko/openstack/designate/__init__.py
tobiko/openstack/designate/_client.py
tobiko/openstack/designate/_constants.py
tobiko/openstack/designate/_zone.py
tobiko/openstack/glance/__init__.py
tobiko/openstack/glance/_client.py
tobiko/openstack/glance/_image.py
tobiko/openstack/glance/_io.py
tobiko/openstack/glance/config.py
tobiko/openstack/heat/__init__.py
tobiko/openstack/heat/_client.py
tobiko/openstack/heat/_resource.py
tobiko/openstack/heat/_stack.py
tobiko/openstack/heat/_template.py
tobiko/openstack/heat/config.py
tobiko/openstack/ironic/__init__.py
tobiko/openstack/ironic/_client.py
tobiko/openstack/ironic/_node.py
tobiko/openstack/keystone/__init__.py
tobiko/openstack/keystone/_client.py
tobiko/openstack/keystone/_clouds_file.py
tobiko/openstack/keystone/_credentials.py
tobiko/openstack/keystone/_resource.py
tobiko/openstack/keystone/_services.py
tobiko/openstack/keystone/_session.py
tobiko/openstack/keystone/config.py
tobiko/openstack/manila/__init__.py
tobiko/openstack/manila/_client.py
tobiko/openstack/manila/_constants.py
tobiko/openstack/manila/_exceptions.py
tobiko-0.8.23.dist-info/licenses/AUTHORS
tobiko-0.8.23.dist-info/licenses/LICENSE
tobiko-0.8.23.dist-info/METADATA
tobiko-0.8.23.dist-info/WHEEL
tobiko-0.8.23.dist-info/entry_points.txt
tobiko-0.8.23.dist-info/pbr.json
tobiko-0.8.23.dist-info/top_level.txt
tobiko-0.8.23.dist-info/RECORD
