Metadata-Version: 2.4
Name: tobiko
Version: 0.8.23
Summary: OpenStack Testing Upgrades Library
Home-page: https://tobiko.readthedocs.io/
Author: OpenStack
Author-email: openstack-discuss@lists.openstack.org
Keywords: setup,distutils
Classifier: Environment :: OpenStack
Classifier: Intended Audience :: Information Technology
Classifier: Intended Audience :: System Administrators
Classifier: License :: OSI Approved :: Apache Software License
Classifier: Operating System :: POSIX :: Linux
Classifier: Programming Language :: Python :: 3
Classifier: Programming Language :: Python :: 3.9
Classifier: Programming Language :: Python :: 3.10
Classifier: Programming Language :: Python :: 3.11
Classifier: Programming Language :: Python :: 3.12
Classifier: Programming Language :: Python :: 3.13
Requires-Python: >=3.9
License-File: LICENSE
License-File: AUTHORS
Requires-Dist: fixtures>=3.0.0
Requires-Dist: keystoneauth1>=4.3.0
Requires-Dist: metalsmith>=1.6.2
Requires-Dist: netaddr>=0.8.0
Requires-Dist: neutron-lib>=2.7.0
Requires-Dist: openstacksdk>=0.31.2
Requires-Dist: oslo.concurrency>=3.26.0
Requires-Dist: oslo.config>=8.4.0
Requires-Dist: oslo.log>=4.4.0
Requires-Dist: oslo.utils>=4.12.3
Requires-Dist: packaging>=20.4
Requires-Dist: paramiko>=2.9.2
Requires-Dist: pbr>=5.5.1
Requires-Dist: psutil>=5.8.0
Requires-Dist: python-designateclient>=4.4.0
Requires-Dist: python-glanceclient>=3.2.2
Requires-Dist: python-heatclient>=2.3.0
Requires-Dist: python-ironicclient>=4.6.1
Requires-Dist: python-manilaclient>=4.5.1
Requires-Dist: python-neutronclient>=7.2.1
Requires-Dist: python-novaclient>=17.2.1
Requires-Dist: python-octaviaclient>=2.2.0
Requires-Dist: python-openstackclient>=5.4.0
Requires-Dist: PyYAML>=5.4.1
Requires-Dist: sshtunnel>=0.3.1
Requires-Dist: testtools>=2.5.0
Requires-Dist: setuptools!=24.0.0,!=34.0.0,!=34.0.1,!=34.0.2,!=34.0.3,!=34.1.0,!=34.1.1,!=34.2.0,!=34.3.0,!=34.3.1,!=34.3.2,!=36.2.0,>=21.0.0; python_version >= "3.12"
Dynamic: author
Dynamic: author-email
Dynamic: classifier
Dynamic: description
Dynamic: home-page
Dynamic: keywords
Dynamic: license-file
Dynamic: provides-extra
Dynamic: requires-dist
Dynamic: requires-python
Dynamic: summary
